<?xml version="1.0" encoding="UTF-8"?>
<thing:thing-descriptions bindingId="veluxklf200"
    xmlns:xsi="http://www.w3.org/2001/XMLSchema-instance"
    xmlns:thing="https://openhab.org/schemas/thing-description/v1.0.0"
    xsi:schemaLocation="https://openhab.org/schemas/thing-description/v1.0.0 https://openhab.org/schemas/thing-description-1.0.0.xsd">

	<channel-type id="scene_trigger">
		<item-type>Switch</item-type>
		<label>Execute</label>
		<description>Allows execution of a predefined scene.</description>
		<category>Switch</category>
		<state readOnly="false"></state>
	</channel-type>

	<channel-type id="position-control">
		<item-type>Rollershutter</item-type>
		<label>Control</label>
		<description>Actuator position control (Up, Down, closure 0-100%)</description>
		<state readOnly="false"></state>
	</channel-type>
</thing:thing-descriptions>